glhf/__init__.py
glhf/__main__.py
glhf/base.py
glhf/bot.py
glhf/cli.py
glhf/gui.py
glhf/typing.py
glhf/resource/Quicksand-Bold.ttf
glhf/resource/city.png
glhf/resource/crown.png
glhf/resource/mountain.png
glhf/resource/obstacle.png
glhf/server/__init__.py
glhf/server/_local.py
glhf/server/_socketio.py
glhf/utils/__init__.py
glhf/utils/map.py
glhf/utils/method.py
glhf-0.0.1.dev6.dist-info/LICENSE
glhf-0.0.1.dev6.dist-info/METADATA
glhf-0.0.1.dev6.dist-info/WHEEL
glhf-0.0.1.dev6.dist-info/top_level.txt
glhf-0.0.1.dev6.dist-info/RECORD
