Metadata-Version: 2.1
Name: glhf
Version: 0.0.1.dev6
Summary: Good luck, have fun! A generals.io bot framework.
Author-email: Hong-Chang Huang <seer852741@gmail.com>
License: GNU GENERAL PUBLIC LICENSE
Keywords: egg,bacon,sausage,tomatoes,Lobster Thermidor
Classifier: Development Status :: 2 - Pre-Alpha
Classifier: Topic :: Software Development :: Libraries
Classifier: Topic :: Games/Entertainment :: Real Time Strategy
Classifier: Topic :: Games/Entertainment :: Simulation
Classifier: License :: OSI Approved :: GNU General Public License v2 (GPLv2)
Classifier: Programming Language :: Python :: 3.12
Requires-Python: >=3.12
License-File: LICENSE
Requires-Dist: pygame-ce ==2.4.1
Requires-Dist: python-socketio[asyncio_client] ==5.11.1
Requires-Dist: ortools ==9.9.3963
Requires-Dist: igraph ==0.11.4
Requires-Dist: fire ==0.6.0
Requires-Dist: rich ==13.7.1
